crypto_data_cache/__init__.py
crypto_data_cache/__main__.py
crypto_data_cache/client.py
crypto_data_cache/configurations.py
crypto_data_cache/db_utils.py
crypto_data_cache/download_utils.py
crypto_data_cache/exceptions.py
crypto_data_cache/fetch_utils.py
crypto_data_cache/logging_config.py
crypto_data_cache-0.2.1.dist-info/METADATA
crypto_data_cache-0.2.1.dist-info/WHEEL
crypto_data_cache-0.2.1.dist-info/licenses/LICENSE
crypto_data_cache-0.2.1.dist-info/RECORD
