Metadata-Version: 2.4
Name: crypto-data-cache
Version: 0.2.1
Summary: A Python library for efficiently downloading, caching, and managing cryptocurrency market data from Binance
Project-URL: Homepage, https://github.com/SithHades/crypto-data-cache
Project-URL: Repository, https://github.com/SithHades/crypto-data-cache.git
Project-URL: Issues, https://github.com/SithHades/crypto-data-cache/issues
Author-email: "Luca B. Knaack" <l.knaack93@gmail.com>
License: MIT
License-File: LICENSE
Keywords: binance,cache,cryptocurrency,data,kline,market-data,trading
Classifier: Development Status :: 3 - Alpha
Classifier: Intended Audience :: Developers
Classifier: Intended Audience :: Financial and Insurance Industry
Classifier: License :: OSI Approved :: MIT License
Classifier: Programming Language :: Python :: 3
Classifier: Programming Language :: Python :: 3.13
Classifier: Topic :: Office/Business :: Financial
Classifier: Topic :: Scientific/Engineering :: Information Analysis
Requires-Python: >=3.13
Requires-Dist: pandas>=2.3.1
Requires-Dist: requests>=2.32.4
Requires-Dist: rich>=14.0.0
Requires-Dist: ruff>=0.12.4
Requires-Dist: ty>=0.0.1a15
